jetengine/__init__.py
jetengine/connection.py
jetengine/database.py
jetengine/document.py
jetengine/errors.py
jetengine/metaclasses.py
jetengine/queryset.py
jetengine/utils.py
jetengine/aggregation/__init__.py
jetengine/aggregation/avg.py
jetengine/aggregation/base.py
jetengine/aggregation/sum.py
jetengine/fields/__init__.py
jetengine/fields/base_field.py
jetengine/fields/binary_field.py
jetengine/fields/boolean_field.py
jetengine/fields/datetime_field.py
jetengine/fields/decimal_field.py
jetengine/fields/dict_field.py
jetengine/fields/dynamic_field.py
jetengine/fields/email_field.py
jetengine/fields/embedded_document_field.py
jetengine/fields/float_field.py
jetengine/fields/int_field.py
jetengine/fields/json_field.py
jetengine/fields/list_field.py
jetengine/fields/objectid_field.py
jetengine/fields/reference_field.py
jetengine/fields/string_field.py
jetengine/fields/url_field.py
jetengine/fields/uuid_field.py
jetengine/query/__init__.py
jetengine/query/base.py
jetengine/query/contains.py
jetengine/query/ends_with.py
jetengine/query/exact.py
jetengine/query/exists.py
jetengine/query/greater_than.py
jetengine/query/greater_than_or_equal.py
jetengine/query/i_contains.py
jetengine/query/i_ends_with.py
jetengine/query/i_exact.py
jetengine/query/i_starts_with.py
jetengine/query/in_operator.py
jetengine/query/is_null.py
jetengine/query/lesser_than.py
jetengine/query/lesser_than_or_equal.py
jetengine/query/not_equal.py
jetengine/query/not_operator.py
jetengine/query/starts_with.py
jetengine/query_builder/__init__.py
jetengine/query_builder/field_list.py
jetengine/query_builder/node.py
jetengine/query_builder/transform.py
jetengine-0.1.3.dist-info/LICENSE
jetengine-0.1.3.dist-info/METADATA
jetengine-0.1.3.dist-info/WHEEL
jetengine-0.1.3.dist-info/top_level.txt
jetengine-0.1.3.dist-info/RECORD
