Metadata-Version: 2.1
Name: jetengine
Version: 0.1.3
Summary: The no-nonsense asyncio MongoDB ODM for Python 3.5+.
Home-page: https://github.com/kpdemetriou/jetengine
Author: Phil Demetriou
Author-email: inbox@philonas.net
License: BSD
Platform: UNKNOWN
Classifier: Development Status :: 4 - Beta
Classifier: Intended Audience :: Developers
Classifier: License :: OSI Approved :: BSD License
Classifier: Operating System :: OS Independent
Classifier: Programming Language :: Python
Classifier: Programming Language :: Python :: 3 :: Only
Classifier: Programming Language :: Python :: 3.5
Classifier: Programming Language :: Python :: 3.6
Classifier: Programming Language :: Python :: 3.7
Classifier: Topic :: Database
Classifier: Topic :: Software Development :: Libraries :: Python Modules
Requires-Dist: easydict
Requires-Dist: pymongo (==3.6)
Requires-Dist: motor (==1.3.1)
